testzmnthy/__init__.py
testzmnthy/decorator.py
testzmnthy/test_start.py
testzmnthy-1.1.0.dist-info/METADATA
testzmnthy-1.1.0.dist-info/WHEEL
testzmnthy-1.1.0.dist-info/top_level.txt
testzmnthy-1.1.0.dist-info/RECORD
